{
    "AddressDB": [
      {
        "id": 1,
        "name": "Shruthi",
        "address": "Btm layout",
        "city": "Bangalore",
        "state": "Karnataka",
        "phone": "9110884694",
        "pincode": "560076"
      },
      {
        "id": 2,
        "name": "Ananya",
        "address": "NCR Layout",
        "city": "Bangalore",
        "state": "Karnataka",
        "phone": "9535082363",
        "pincode": "560070"
      },
      {
        "id": 3,
        "name": "Sneha",
        "address": "Mico Layout",
        "city": "Bangalore",
        "state": "Karnataka",
        "phone": "7894561236",
        "pincode": "560071"
      }
    ]
  }